Metadata-Version: 1.1
Name: nadaprafazer
Version: 0.1.1
Summary: Simple crawler to list top reddit threads. Includes webhook stuff
Home-page: https://github.com/jucacrispim/desafios/crawlers
Author: Juca Crispim
Author-email: juca@poraodojuca.net
License: GPL
Platform: UNKNOWN
Provides: nadaprafazer
